idaenv/__init__.py
idaenv/cmd_utils.py
idaenv/command_line.py
idaenv/manager.py
idaenv/utils.py
idaenv-0.4.0.dist-info/METADATA
idaenv-0.4.0.dist-info/WHEEL
idaenv-0.4.0.dist-info/entry_points.txt
idaenv-0.4.0.dist-info/top_level.txt
idaenv-0.4.0.dist-info/RECORD
