Metadata-Version: 2.1
Name: idaenv
Version: 0.4.0
Summary: IDA Pro plugin manager.
Home-page: UNKNOWN
License: MIT
Platform: UNKNOWN
Classifier: Natural Language :: English
Classifier: Programming Language :: Python
Classifier: Programming Language :: Python :: 2
Classifier: Programming Language :: Python :: 3
